fermigraph/__about__.py
fermigraph/__init__.py
fermigraph/graph.py
fermigraph/state.py
fermigraph-0.0.1.dist-info/METADATA
fermigraph-0.0.1.dist-info/WHEEL
fermigraph-0.0.1.dist-info/entry_points.txt
fermigraph-0.0.1.dist-info/license_files/LICENSE.txt
fermigraph-0.0.1.dist-info/RECORD
